jemm/__init__.py
jemm/covariate.py
jemm/data_table.py
jemm/genomic_annotation.py
jemm/gtex_utils.py
jemm/jem_glm.py
jemm/junction.py
jemm/kallisto_helper.py
jemm/meta_loader.py
jemm/model.py
jemm/plots.py
jemm/rmats_helper.py
jemm/suppa_helper.py
jemm/transcript.py
jemm/utils.py
jemm-0.0.2.dist-info/LICENSE
jemm-0.0.2.dist-info/METADATA
jemm-0.0.2.dist-info/WHEEL
jemm-0.0.2.dist-info/top_level.txt
jemm-0.0.2.dist-info/RECORD
