Metadata-Version: 2.1
Name: jemm
Version: 0.0.2
Summary: joint exon-measure model
Home-page: https://github.com/zhanglab-aim/JEMM
Author: zzjfrank
Author-email: zijun.zhang@cshs.org
License: GPL-3.0
Platform: UNKNOWN
License-File: LICENSE
